{
  "data": {
    "cards-stack-settings-title": "Settings",
    "cards-stack-settings-subtitle": "Change your account settings, language, the way app looks and behaves",
    "cards-stack-settings-display": "Display",
    "cards-stack-settings-sorting": "Sorting",
    "cards-stack-settings-locale": "Language",
    "cards-stack-settings-support": "Support",
    "cards-stack-settings-general": "General",
    "cards-stack-settings-sign-in": "Authenticate",
    "cards-stack-settings-sign-out": "Log Out",
    "cards-stack-settings-account": "Account",
    "cards-stack-settings-sorting-first-last": "First, Last",
    "cards-stack-settings-sorting-last-first": "Last, First"
  }
}
