{
  "data": {
    "new-stack": "New stack",
    "new-stack-subtitle": "A custom stack of cards",
    "custom-cards-more" : "More options",
    "custom-cards-type-here": "Type here",
    "custom-cards-add-cards": "Add cards",
    "custom-cards-edit-card": "Edit",
    "custom-cards-delete-card": "Delete",
    "custom-cards-add-to-favourites": "Add to favorites",
    "custom-cards-remove-from-stack": "Remove from stack",
    "custom-cards-empty-heading": "Let's add some cards",
    "custom-cards-empty-text-add": "You can add live or phonebook cards to this stack.",
    "custom-cards-empty-facebook-button": "Add cards"
  }
}
